storyforge/StoryForge.py
storyforge/__init__.py
storyforge/anthropic_backend.py
storyforge/checkpoint.py
storyforge/config.py
storyforge/context.py
storyforge/gemini_backend.py
storyforge/llm_backend.py
storyforge/model_discovery.py
storyforge/openai_backend.py
storyforge/phase_executor.py
storyforge/prompt.py
storyforge/schema/__init__.py
storyforge/schema/cli_integration.py
storyforge/schema/config_schema.py
storyforge/schema/core.py
storyforge/schema/validation.py
storyforge-0.0.6.dist-info/licenses/LICENSE
storyforge-0.0.6.dist-info/METADATA
storyforge-0.0.6.dist-info/WHEEL
storyforge-0.0.6.dist-info/entry_points.txt
storyforge-0.0.6.dist-info/top_level.txt
storyforge-0.0.6.dist-info/RECORD
