Metadata-Version: 2.4
Name: StoryForge
Version: 0.0.6
Summary: A TUI app that generates short stories and AI images from prompts using a language model.
Author: wom
License-Expression: MIT
Project-URL: Homepage, https://github.com/wom/StoryForge
Project-URL: Repository, https://github.com/wom/StoryForge
Project-URL: Bug Tracker, https://github.com/wom/StoryForge/issues
Project-URL: Documentation, https://github.com/wom/StoryForge#readme
Keywords: ai,stories,children,cli,gemini,image-generation,text-generation,tui,storytelling,terminal
Classifier: Development Status :: 4 - Beta
Classifier: Environment :: Console
Classifier: Intended Audience :: Developers
Classifier: Operating System :: OS Independent
Classifier: Programming Language :: Python :: 3
Classifier: Programming Language :: Python :: 3.8
Classifier: Programming Language :: Python :: 3.9
Classifier: Programming Language :: Python :: 3.10
Classifier: Programming Language :: Python :: 3.11
Classifier: Programming Language :: Python :: 3.12
Classifier: Topic :: Text Processing :: General
Classifier: Topic :: Multimedia :: Graphics
Classifier: Topic :: Games/Entertainment
Classifier: Topic :: Artistic Software
Classifier: Topic :: Education
Classifier: Typing :: Typed
Requires-Python: >=3.8
License-File: LICENSE
Requires-Dist: google-genai>=1.23.0
Requires-Dist: anthropic>=0.28.0
Requires-Dist: openai>=1.12.0
Requires-Dist: requests>=2.31.0
Requires-Dist: pillow>=11.2.1
Requires-Dist: textual[syntax]>=0.54.1
Requires-Dist: textual-dev>=0.00.1
Requires-Dist: typer>=0.9.0
Requires-Dist: rich>=13.0.0
Requires-Dist: platformdirs>=4.2.0
Requires-Dist: pyyaml>=6.0.0
Provides-Extra: dev
Requires-Dist: pytest>=8.2.0; extra == "dev"
Requires-Dist: pytest-cov>=4.1.0; extra == "dev"
Requires-Dist: coverage>=7.5.0; extra == "dev"
Requires-Dist: ruff>=0.12.1; extra == "dev"
Requires-Dist: mypy>=1.8.0; extra == "dev"
Requires-Dist: pre-commit>=3.6.0; extra == "dev"
Requires-Dist: pip>=25.1.1; extra == "dev"
Requires-Dist: types-PyYAML>=6.0.12; extra == "dev"
Dynamic: license-file
